{"__type__":"sp.SkeletonData","_name":"bonus-ball","skeletonJsonStr":"{\"skeleton\":{\"hash\":\"UmbckBKJC5S/yH5yMf2JI99XQVI\",\"spine\":\"3.6.53\",\"width\":177.87,\"height\":176.87,\"images\":\"../gameplay/\"},\"bones\":[{\"name\":\"root\"},{\"name\":\"all\",\"parent\":\"root\",\"scaleX\":2.075,\"scaleY\":2.075},{\"name\":\"backlight\",\"parent\":\"all\"},{\"name\":\"backlight2\",\"parent\":\"all\"},{\"name\":\"ball\",\"parent\":\"all\"},{\"name\":\"flare\",\"parent\":\"all\"},{\"name\":\"roll\",\"parent\":\"ball\"}],\"slots\":[{\"name\":\"eff/17_0044_94d0033e52bb4448e79787550c38022838f98f376d2b-D2iEEy_fw658-copy-2\",\"bone\":\"backlight\",\"blend\":\"additive\"},{\"name\":\"eff/17_0044_94d0033e52bb4448e79787550c38022838f98f376d2b-D2iEEy_fw658-copy-3\",\"bone\":\"backlight2\",\"blend\":\"additive\"},{\"name\":\"effect/football_PNG52781\",\"bone\":\"roll\",\"attachment\":\"effect/football_PNG52781\"},{\"name\":\"effect/golden-ball\",\"bone\":\"roll\"},{\"name\":\"bonus/oldball\",\"bone\":\"roll\"},{\"name\":\"eff/flare\",\"bone\":\"flare\",\"blend\":\"additive\"},{\"name\":\"bonus/main screen/ball_glow\",\"bone\":\"ball\",\"blend\":\"additive\"}],\"skins\":{\"default\":{\"bonus/main screen/ball_glow\":{\"bonus/main screen/ball_glow\":{\"scaleX\":0.462,\"scaleY\":0.462,\"width\":240,\"height\":241}},\"bonus/oldball\":{\"bonus/oldball\":{\"width\":86,\"height\":86}},\"eff/17_0044_94d0033e52bb4448e79787550c38022838f98f376d2b-D2iEEy_fw658-copy-2\":{\"eff/17_0044_94d0033e52bb4448e79787550c38022838f98f376d2b-D2iEEy_fw658-copy-2\":{\"width\":131,\"height\":131}},\"eff/17_0044_94d0033e52bb4448e79787550c38022838f98f376d2b-D2iEEy_fw658-copy-3\":{\"eff/17_0044_94d0033e52bb4448e79787550c38022838f98f376d2b-D2iEEy_fw658-copy-2\":{\"rotation\":-11.68,\"width\":131,\"height\":131}},\"eff/flare\":{\"eff/flare\":{\"y\":-5.8,\"scaleX\":0.376,\"scaleY\":0.376,\"width\":481,\"height\":445}},\"effect/football_PNG52781\":{\"effect/football_PNG52781\":{\"scaleX\":0.482,\"scaleY\":0.482,\"width\":178,\"height\":177}},\"effect/golden-ball\":{\"effect/golden-football\":{\"width\":87,\"height\":87}}}},\"animations\":{\"active-lose\":{\"slots\":{\"bonus/main screen/ball_glow\":{\"color\":[{\"time\":0,\"color\":\"ffffffff\",\"curve\":\"stepped\"},{\"time\":0.3333,\"color\":\"ffffffff\"},{\"time\":0.5,\"color\":\"ffffff00\"}],\"attachment\":[{\"time\":0,\"name\":\"bonus/main screen/ball_glow\"}]},\"bonus/oldball\":{\"color\":[{\"time\":0.3333,\"color\":\"ffffff00\"},{\"time\":0.5,\"color\":\"aaa8a0ff\"}],\"attachment\":[{\"time\":0.3333,\"name\":\"bonus/oldball\"}]},\"eff/17_0044_94d0033e52bb4448e79787550c38022838f98f376d2b-D2iEEy_fw658-copy-2\":{\"attachment\":[{\"time\":0,\"name\":null}]},\"eff/17_0044_94d0033e52bb4448e79787550c38022838f98f376d2b-D2iEEy_fw658-copy-3\":{\"attachment\":[{\"time\":0,\"name\":null}]},\"eff/flare\":{\"attachment\":[{\"time\":0,\"name\":null}]},\"effect/football_PNG52781\":{\"color\":[{\"time\":0,\"color\":\"ffffffff\",\"curve\":\"stepped\"},{\"time\":0.3333,\"color\":\"ffffffff\"},{\"time\":0.5,\"color\":\"ffffff00\"}],\"attachment\":[{\"time\":0.5,\"name\":null}]}},\"bones\":{\"roll\":{\"rotate\":[{\"time\":0,\"angle\":0},{\"time\":1,\"angle\":180},{\"time\":2,\"angle\":0}]},\"ball\":{\"scale\":[{\"time\":0,\"x\":1,\"y\":1,\"curve\":[0.25,0,0.75,1]},{\"time\":0.3333,\"x\":0.697,\"y\":0.697,\"curve\":[0.25,0,0.241,1]},{\"time\":0.5,\"x\":1.808,\"y\":1.808,\"curve\":[0.705,0,0.75,1]},{\"time\":1,\"x\":1,\"y\":1,\"curve\":\"stepped\"},{\"time\":2,\"x\":1,\"y\":1}]}}},\"active-win\":{\"slots\":{\"bonus/main screen/ball_glow\":{\"color\":[{\"time\":0,\"color\":\"ffffffff\",\"curve\":\"stepped\"},{\"time\":0.3333,\"color\":\"ffffffff\"},{\"time\":0.6667,\"color\":\"ffffff00\"}],\"attachment\":[{\"time\":0,\"name\":\"bonus/main screen/ball_glow\"}]},\"eff/17_0044_94d0033e52bb4448e79787550c38022838f98f376d2b-D2iEEy_fw658-copy-2\":{\"color\":[{\"time\":0,\"color\":\"ffffff00\",\"curve\":[0.25,0,0.75,1]},{\"time\":0.3333,\"color\":\"ffffffff\"}],\"attachment\":[{\"time\":0,\"name\":\"eff/17_0044_94d0033e52bb4448e79787550c38022838f98f376d2b-D2iEEy_fw658-copy-2\"},{\"time\":0.3333,\"name\":\"eff/17_0044_94d0033e52bb4448e79787550c38022838f98f376d2b-D2iEEy_fw658-copy-2\"}]},\"eff/17_0044_94d0033e52bb4448e79787550c38022838f98f376d2b-D2iEEy_fw658-copy-3\":{\"color\":[{\"time\":0,\"color\":\"ffffff00\",\"curve\":[0.25,0,0.75,1]},{\"time\":0.3333,\"color\":\"ffffffff\"}],\"attachment\":[{\"time\":0,\"name\":\"eff/17_0044_94d0033e52bb4448e79787550c38022838f98f376d2b-D2iEEy_fw658-copy-2\"},{\"time\":0.3333,\"name\":\"eff/17_0044_94d0033e52bb4448e79787550c38022838f98f376d2b-D2iEEy_fw658-copy-2\"}]},\"eff/flare\":{\"color\":[{\"time\":0,\"color\":\"ffffff00\"},{\"time\":0.5,\"color\":\"ffffffff\"},{\"time\":0.9667,\"color\":\"ffffff00\",\"curve\":\"stepped\"},{\"time\":1,\"color\":\"ffffff00\"},{\"time\":1.5,\"color\":\"ffffffff\"},{\"time\":1.9667,\"color\":\"ffffff00\"}],\"attachment\":[{\"time\":0,\"name\":\"eff/flare\"}]},\"effect/football_PNG52781\":{\"color\":[{\"time\":0,\"color\":\"ffffffff\",\"curve\":\"stepped\"},{\"time\":0.3333,\"color\":\"ffffffff\"},{\"time\":0.5,\"color\":\"ffffff00\"}],\"attachment\":[{\"time\":0.5,\"name\":null}]},\"effect/golden-ball\":{\"color\":[{\"time\":0.3333,\"color\":\"ffffff00\"},{\"time\":0.5,\"color\":\"ffffffff\"}],\"attachment\":[{\"time\":0.3333,\"name\":\"effect/golden-football\"}]}},\"bones\":{\"roll\":{\"rotate\":[{\"time\":0,\"angle\":0},{\"time\":1,\"angle\":180},{\"time\":2,\"angle\":0}]},\"ball\":{\"scale\":[{\"time\":0,\"x\":1,\"y\":1,\"curve\":[0.25,0,0.75,1]},{\"time\":0.3333,\"x\":0.697,\"y\":0.697,\"curve\":[0.25,0,0.241,1]},{\"time\":0.5,\"x\":1.808,\"y\":1.808,\"curve\":[0.705,0,0.75,1]},{\"time\":1,\"x\":1,\"y\":1,\"curve\":\"stepped\"},{\"time\":2,\"x\":1,\"y\":1}]},\"backlight\":{\"scale\":[{\"time\":0,\"x\":0.843,\"y\":0.843},{\"time\":1,\"x\":1.142,\"y\":1.142,\"curve\":[0.25,0,0.75,1]},{\"time\":2,\"x\":0.843,\"y\":0.843}]},\"backlight2\":{\"scale\":[{\"time\":0,\"x\":0.992,\"y\":0.992,\"curve\":[0.375,0.5,0.75,1]},{\"time\":0.5,\"x\":0.843,\"y\":0.843,\"curve\":[0.25,0,0.75,1]},{\"time\":1.5,\"x\":1.142,\"y\":1.142,\"curve\":[0.25,0,0.625,0.5]},{\"time\":2,\"x\":0.992,\"y\":0.992}]},\"flare\":{\"scale\":[{\"time\":0,\"x\":0.404,\"y\":0.404,\"curve\":[0,0.23,0.75,1]},{\"time\":0.9667,\"x\":1.37,\"y\":1.37},{\"time\":1,\"x\":0.404,\"y\":0.404,\"curve\":[0,0.23,0.75,1]},{\"time\":1.9667,\"x\":1.37,\"y\":1.37}]}}},\"idle\":{\"slots\":{\"bonus/main screen/ball_glow\":{\"attachment\":[{\"time\":0,\"name\":\"bonus/main screen/ball_glow\"}]},\"eff/17_0044_94d0033e52bb4448e79787550c38022838f98f376d2b-D2iEEy_fw658-copy-2\":{\"attachment\":[{\"time\":0,\"name\":null}]},\"eff/17_0044_94d0033e52bb4448e79787550c38022838f98f376d2b-D2iEEy_fw658-copy-3\":{\"attachment\":[{\"time\":0,\"name\":null}]},\"eff/flare\":{\"attachment\":[{\"time\":0,\"name\":null}]}},\"bones\":{\"roll\":{\"rotate\":[{\"time\":0,\"angle\":0},{\"time\":1,\"angle\":180},{\"time\":2,\"angle\":0}]}}},\"idle-lose\":{\"slots\":{\"bonus/oldball\":{\"color\":[{\"time\":0,\"color\":\"aaa8a0ff\"}],\"attachment\":[{\"time\":0,\"name\":\"bonus/oldball\"}]},\"eff/17_0044_94d0033e52bb4448e79787550c38022838f98f376d2b-D2iEEy_fw658-copy-2\":{\"attachment\":[{\"time\":0,\"name\":null}]},\"eff/17_0044_94d0033e52bb4448e79787550c38022838f98f376d2b-D2iEEy_fw658-copy-3\":{\"attachment\":[{\"time\":0,\"name\":null}]},\"eff/flare\":{\"attachment\":[{\"time\":0,\"name\":null}]},\"effect/football_PNG52781\":{\"color\":[{\"time\":0,\"color\":\"ffffff00\"}],\"attachment\":[{\"time\":0,\"name\":null}]}},\"bones\":{\"roll\":{\"rotate\":[{\"time\":0,\"angle\":0},{\"time\":1,\"angle\":180},{\"time\":2,\"angle\":0}]},\"ball\":{\"scale\":[{\"time\":0,\"x\":1,\"y\":1,\"curve\":\"stepped\"},{\"time\":2,\"x\":1,\"y\":1}]}}},\"idle-win\":{\"slots\":{\"eff/17_0044_94d0033e52bb4448e79787550c38022838f98f376d2b-D2iEEy_fw658-copy-2\":{\"color\":[{\"time\":0,\"color\":\"ffffff00\",\"curve\":[0.25,0,0.75,1]},{\"time\":0.3333,\"color\":\"ffffffff\"}],\"attachment\":[{\"time\":0,\"name\":\"eff/17_0044_94d0033e52bb4448e79787550c38022838f98f376d2b-D2iEEy_fw658-copy-2\"},{\"time\":0.3333,\"name\":\"eff/17_0044_94d0033e52bb4448e79787550c38022838f98f376d2b-D2iEEy_fw658-copy-2\"}]},\"eff/17_0044_94d0033e52bb4448e79787550c38022838f98f376d2b-D2iEEy_fw658-copy-3\":{\"color\":[{\"time\":0,\"color\":\"ffffff00\",\"curve\":[0.25,0,0.75,1]},{\"time\":0.3333,\"color\":\"ffffffff\"}],\"attachment\":[{\"time\":0,\"name\":\"eff/17_0044_94d0033e52bb4448e79787550c38022838f98f376d2b-D2iEEy_fw658-copy-2\"},{\"time\":0.3333,\"name\":\"eff/17_0044_94d0033e52bb4448e79787550c38022838f98f376d2b-D2iEEy_fw658-copy-2\"}]},\"eff/flare\":{\"color\":[{\"time\":0,\"color\":\"ffffff00\"},{\"time\":0.5,\"color\":\"ffffffff\"},{\"time\":0.9667,\"color\":\"ffffff00\",\"curve\":\"stepped\"},{\"time\":1,\"color\":\"ffffff00\"},{\"time\":1.5,\"color\":\"ffffffff\"},{\"time\":1.9667,\"color\":\"ffffff00\"}],\"attachment\":[{\"time\":0,\"name\":\"eff/flare\"}]},\"effect/football_PNG52781\":{\"color\":[{\"time\":0,\"color\":\"ffffffff\"}],\"attachment\":[{\"time\":0,\"name\":\"effect/football_PNG52781\"}]},\"effect/golden-ball\":{\"color\":[{\"time\":0,\"color\":\"ffffffff\"}],\"attachment\":[{\"time\":0,\"name\":\"effect/golden-football\"}]}},\"bones\":{\"roll\":{\"rotate\":[{\"time\":0,\"angle\":0},{\"time\":1,\"angle\":180},{\"time\":2,\"angle\":0}]},\"ball\":{\"scale\":[{\"time\":0,\"x\":1,\"y\":1,\"curve\":\"stepped\"},{\"time\":2,\"x\":1,\"y\":1}]},\"backlight\":{\"scale\":[{\"time\":0,\"x\":0.843,\"y\":0.843},{\"time\":1,\"x\":1.142,\"y\":1.142,\"curve\":[0.25,0,0.75,1]},{\"time\":2,\"x\":0.843,\"y\":0.843}]},\"backlight2\":{\"scale\":[{\"time\":0,\"x\":0.992,\"y\":0.992,\"curve\":[0.375,0.5,0.75,1]},{\"time\":0.5,\"x\":0.843,\"y\":0.843,\"curve\":[0.25,0,0.75,1]},{\"time\":1.5,\"x\":1.142,\"y\":1.142,\"curve\":[0.25,0,0.625,0.5]},{\"time\":2,\"x\":0.992,\"y\":0.992}]},\"flare\":{\"scale\":[{\"time\":0,\"x\":0.404,\"y\":0.404,\"curve\":[0,0.23,0.75,1]},{\"time\":0.9667,\"x\":1.37,\"y\":1.37},{\"time\":1,\"x\":0.404,\"y\":0.404,\"curve\":[0,0.23,0.75,1]},{\"time\":1.9667,\"x\":1.37,\"y\":1.37}]}}}}}","_skeletonJson":{"skeleton":{"hash":"UmbckBKJC5S/yH5yMf2JI99XQVI","spine":"3.6.53","width":177.87,"height":176.87,"images":"../gameplay/"},"bones":[{"name":"root"},{"name":"all","parent":"root","scaleX":2.075,"scaleY":2.075},{"name":"backlight","parent":"all"},{"name":"backlight2","parent":"all"},{"name":"ball","parent":"all"},{"name":"flare","parent":"all"},{"name":"roll","parent":"ball"}],"slots":[{"name":"eff/17_0044_94d0033e52bb4448e79787550c38022838f98f376d2b-D2iEEy_fw658-copy-2","bone":"backlight","blend":"additive"},{"name":"eff/17_0044_94d0033e52bb4448e79787550c38022838f98f376d2b-D2iEEy_fw658-copy-3","bone":"backlight2","blend":"additive"},{"name":"effect/football_PNG52781","bone":"roll","attachment":"effect/football_PNG52781"},{"name":"effect/golden-ball","bone":"roll"},{"name":"bonus/oldball","bone":"roll"},{"name":"eff/flare","bone":"flare","blend":"additive"},{"name":"bonus/main screen/ball_glow","bone":"ball","blend":"additive"}],"skins":{"default":{"bonus/main screen/ball_glow":{"bonus/main screen/ball_glow":{"scaleX":0.462,"scaleY":0.462,"width":240,"height":241}},"bonus/oldball":{"bonus/oldball":{"width":86,"height":86}},"eff/17_0044_94d0033e52bb4448e79787550c38022838f98f376d2b-D2iEEy_fw658-copy-2":{"eff/17_0044_94d0033e52bb4448e79787550c38022838f98f376d2b-D2iEEy_fw658-copy-2":{"width":131,"height":131}},"eff/17_0044_94d0033e52bb4448e79787550c38022838f98f376d2b-D2iEEy_fw658-copy-3":{"eff/17_0044_94d0033e52bb4448e79787550c38022838f98f376d2b-D2iEEy_fw658-copy-2":{"rotation":-11.68,"width":131,"height":131}},"eff/flare":{"eff/flare":{"y":-5.8,"scaleX":0.376,"scaleY":0.376,"width":481,"height":445}},"effect/football_PNG52781":{"effect/football_PNG52781":{"scaleX":0.482,"scaleY":0.482,"width":178,"height":177}},"effect/golden-ball":{"effect/golden-football":{"width":87,"height":87}}}},"animations":{"active-lose":{"slots":{"bonus/main screen/ball_glow":{"color":[{"time":0,"color":"ffffffff","curve":"stepped"},{"time":0.3333,"color":"ffffffff"},{"time":0.5,"color":"ffffff00"}],"attachment":[{"time":0,"name":"bonus/main screen/ball_glow"}]},"bonus/oldball":{"color":[{"time":0.3333,"color":"ffffff00"},{"time":0.5,"color":"aaa8a0ff"}],"attachment":[{"time":0.3333,"name":"bonus/oldball"}]},"eff/17_0044_94d0033e52bb4448e79787550c38022838f98f376d2b-D2iEEy_fw658-copy-2":{"attachment":[{"time":0,"name":null}]},"eff/17_0044_94d0033e52bb4448e79787550c38022838f98f376d2b-D2iEEy_fw658-copy-3":{"attachment":[{"time":0,"name":null}]},"eff/flare":{"attachment":[{"time":0,"name":null}]},"effect/football_PNG52781":{"color":[{"time":0,"color":"ffffffff","curve":"stepped"},{"time":0.3333,"color":"ffffffff"},{"time":0.5,"color":"ffffff00"}],"attachment":[{"time":0.5,"name":null}]}},"bones":{"roll":{"rotate":[{"time":0,"angle":0},{"time":1,"angle":180},{"time":2,"angle":0}]},"ball":{"scale":[{"time":0,"x":1,"y":1,"curve":[0.25,0,0.75,1]},{"time":0.3333,"x":0.697,"y":0.697,"curve":[0.25,0,0.241,1]},{"time":0.5,"x":1.808,"y":1.808,"curve":[0.705,0,0.75,1]},{"time":1,"x":1,"y":1,"curve":"stepped"},{"time":2,"x":1,"y":1}]}}},"active-win":{"slots":{"bonus/main screen/ball_glow":{"color":[{"time":0,"color":"ffffffff","curve":"stepped"},{"time":0.3333,"color":"ffffffff"},{"time":0.6667,"color":"ffffff00"}],"attachment":[{"time":0,"name":"bonus/main screen/ball_glow"}]},"eff/17_0044_94d0033e52bb4448e79787550c38022838f98f376d2b-D2iEEy_fw658-copy-2":{"color":[{"time":0,"color":"ffffff00","curve":[0.25,0,0.75,1]},{"time":0.3333,"color":"ffffffff"}],"attachment":[{"time":0,"name":"eff/17_0044_94d0033e52bb4448e79787550c38022838f98f376d2b-D2iEEy_fw658-copy-2"},{"time":0.3333,"name":"eff/17_0044_94d0033e52bb4448e79787550c38022838f98f376d2b-D2iEEy_fw658-copy-2"}]},"eff/17_0044_94d0033e52bb4448e79787550c38022838f98f376d2b-D2iEEy_fw658-copy-3":{"color":[{"time":0,"color":"ffffff00","curve":[0.25,0,0.75,1]},{"time":0.3333,"color":"ffffffff"}],"attachment":[{"time":0,"name":"eff/17_0044_94d0033e52bb4448e79787550c38022838f98f376d2b-D2iEEy_fw658-copy-2"},{"time":0.3333,"name":"eff/17_0044_94d0033e52bb4448e79787550c38022838f98f376d2b-D2iEEy_fw658-copy-2"}]},"eff/flare":{"color":[{"time":0,"color":"ffffff00"},{"time":0.5,"color":"ffffffff"},{"time":0.9667,"color":"ffffff00","curve":"stepped"},{"time":1,"color":"ffffff00"},{"time":1.5,"color":"ffffffff"},{"time":1.9667,"color":"ffffff00"}],"attachment":[{"time":0,"name":"eff/flare"}]},"effect/football_PNG52781":{"color":[{"time":0,"color":"ffffffff","curve":"stepped"},{"time":0.3333,"color":"ffffffff"},{"time":0.5,"color":"ffffff00"}],"attachment":[{"time":0.5,"name":null}]},"effect/golden-ball":{"color":[{"time":0.3333,"color":"ffffff00"},{"time":0.5,"color":"ffffffff"}],"attachment":[{"time":0.3333,"name":"effect/golden-football"}]}},"bones":{"roll":{"rotate":[{"time":0,"angle":0},{"time":1,"angle":180},{"time":2,"angle":0}]},"ball":{"scale":[{"time":0,"x":1,"y":1,"curve":[0.25,0,0.75,1]},{"time":0.3333,"x":0.697,"y":0.697,"curve":[0.25,0,0.241,1]},{"time":0.5,"x":1.808,"y":1.808,"curve":[0.705,0,0.75,1]},{"time":1,"x":1,"y":1,"curve":"stepped"},{"time":2,"x":1,"y":1}]},"backlight":{"scale":[{"time":0,"x":0.843,"y":0.843},{"time":1,"x":1.142,"y":1.142,"curve":[0.25,0,0.75,1]},{"time":2,"x":0.843,"y":0.843}]},"backlight2":{"scale":[{"time":0,"x":0.992,"y":0.992,"curve":[0.375,0.5,0.75,1]},{"time":0.5,"x":0.843,"y":0.843,"curve":[0.25,0,0.75,1]},{"time":1.5,"x":1.142,"y":1.142,"curve":[0.25,0,0.625,0.5]},{"time":2,"x":0.992,"y":0.992}]},"flare":{"scale":[{"time":0,"x":0.404,"y":0.404,"curve":[0,0.23,0.75,1]},{"time":0.9667,"x":1.37,"y":1.37},{"time":1,"x":0.404,"y":0.404,"curve":[0,0.23,0.75,1]},{"time":1.9667,"x":1.37,"y":1.37}]}}},"idle":{"slots":{"bonus/main screen/ball_glow":{"attachment":[{"time":0,"name":"bonus/main screen/ball_glow"}]},"eff/17_0044_94d0033e52bb4448e79787550c38022838f98f376d2b-D2iEEy_fw658-copy-2":{"attachment":[{"time":0,"name":null}]},"eff/17_0044_94d0033e52bb4448e79787550c38022838f98f376d2b-D2iEEy_fw658-copy-3":{"attachment":[{"time":0,"name":null}]},"eff/flare":{"attachment":[{"time":0,"name":null}]}},"bones":{"roll":{"rotate":[{"time":0,"angle":0},{"time":1,"angle":180},{"time":2,"angle":0}]}}},"idle-lose":{"slots":{"bonus/oldball":{"color":[{"time":0,"color":"aaa8a0ff"}],"attachment":[{"time":0,"name":"bonus/oldball"}]},"eff/17_0044_94d0033e52bb4448e79787550c38022838f98f376d2b-D2iEEy_fw658-copy-2":{"attachment":[{"time":0,"name":null}]},"eff/17_0044_94d0033e52bb4448e79787550c38022838f98f376d2b-D2iEEy_fw658-copy-3":{"attachment":[{"time":0,"name":null}]},"eff/flare":{"attachment":[{"time":0,"name":null}]},"effect/football_PNG52781":{"color":[{"time":0,"color":"ffffff00"}],"attachment":[{"time":0,"name":null}]}},"bones":{"roll":{"rotate":[{"time":0,"angle":0},{"time":1,"angle":180},{"time":2,"angle":0}]},"ball":{"scale":[{"time":0,"x":1,"y":1,"curve":"stepped"},{"time":2,"x":1,"y":1}]}}},"idle-win":{"slots":{"eff/17_0044_94d0033e52bb4448e79787550c38022838f98f376d2b-D2iEEy_fw658-copy-2":{"color":[{"time":0,"color":"ffffff00","curve":[0.25,0,0.75,1]},{"time":0.3333,"color":"ffffffff"}],"attachment":[{"time":0,"name":"eff/17_0044_94d0033e52bb4448e79787550c38022838f98f376d2b-D2iEEy_fw658-copy-2"},{"time":0.3333,"name":"eff/17_0044_94d0033e52bb4448e79787550c38022838f98f376d2b-D2iEEy_fw658-copy-2"}]},"eff/17_0044_94d0033e52bb4448e79787550c38022838f98f376d2b-D2iEEy_fw658-copy-3":{"color":[{"time":0,"color":"ffffff00","curve":[0.25,0,0.75,1]},{"time":0.3333,"color":"ffffffff"}],"attachment":[{"time":0,"name":"eff/17_0044_94d0033e52bb4448e79787550c38022838f98f376d2b-D2iEEy_fw658-copy-2"},{"time":0.3333,"name":"eff/17_0044_94d0033e52bb4448e79787550c38022838f98f376d2b-D2iEEy_fw658-copy-2"}]},"eff/flare":{"color":[{"time":0,"color":"ffffff00"},{"time":0.5,"color":"ffffffff"},{"time":0.9667,"color":"ffffff00","curve":"stepped"},{"time":1,"color":"ffffff00"},{"time":1.5,"color":"ffffffff"},{"time":1.9667,"color":"ffffff00"}],"attachment":[{"time":0,"name":"eff/flare"}]},"effect/football_PNG52781":{"color":[{"time":0,"color":"ffffffff"}],"attachment":[{"time":0,"name":"effect/football_PNG52781"}]},"effect/golden-ball":{"color":[{"time":0,"color":"ffffffff"}],"attachment":[{"time":0,"name":"effect/golden-football"}]}},"bones":{"roll":{"rotate":[{"time":0,"angle":0},{"time":1,"angle":180},{"time":2,"angle":0}]},"ball":{"scale":[{"time":0,"x":1,"y":1,"curve":"stepped"},{"time":2,"x":1,"y":1}]},"backlight":{"scale":[{"time":0,"x":0.843,"y":0.843},{"time":1,"x":1.142,"y":1.142,"curve":[0.25,0,0.75,1]},{"time":2,"x":0.843,"y":0.843}]},"backlight2":{"scale":[{"time":0,"x":0.992,"y":0.992,"curve":[0.375,0.5,0.75,1]},{"time":0.5,"x":0.843,"y":0.843,"curve":[0.25,0,0.75,1]},{"time":1.5,"x":1.142,"y":1.142,"curve":[0.25,0,0.625,0.5]},{"time":2,"x":0.992,"y":0.992}]},"flare":{"scale":[{"time":0,"x":0.404,"y":0.404,"curve":[0,0.23,0.75,1]},{"time":0.9667,"x":1.37,"y":1.37},{"time":1,"x":0.404,"y":0.404,"curve":[0,0.23,0.75,1]},{"time":1.9667,"x":1.37,"y":1.37}]}}}}},"_atlasText":"\nbonus-ball.png\nsize: 1024,1024\nformat: RGBA8888\nfilter: Linear,Linear\nrepeat: none\nbonus/main screen/ball_glow\n  rotate: false\n  xy: 2, 135\n  size: 240, 241\n  orig: 240, 241\n  offset: 0, 0\n  index: -1\nbonus/oldball\n  rotate: false\n  xy: 485, 558\n  size: 86, 86\n  orig: 86, 86\n  offset: 0, 0\n  index: -1\neff/17_0044_94d0033e52bb4448e79787550c38022838f98f376d2b-D2iEEy_fw658-copy-2\n  rotate: false\n  xy: 2, 2\n  size: 131, 131\n  orig: 131, 131\n  offset: 0, 0\n  index: -1\neff/flare\n  rotate: false\n  xy: 2, 378\n  size: 481, 445\n  orig: 481, 445\n  offset: 0, 0\n  index: -1\neffect/football_PNG52781\n  rotate: false\n  xy: 485, 646\n  size: 178, 177\n  orig: 178, 177\n  offset: 0, 0\n  index: -1\neffect/golden-football\n  rotate: false\n  xy: 244, 289\n  size: 87, 87\n  orig: 87, 87\n  offset: 0, 0\n  index: -1\n","textures":[{"__uuid__":"cfVdCwBeJP76AycSMcOwn6"}],"textureNames":["bonus-ball.png"]}